fastapi_full_stack/__init__.py
fastapi_full_stack/main.py
fastapi_full_stack_launch-1.1.0.dist-info/METADATA
fastapi_full_stack_launch-1.1.0.dist-info/WHEEL
fastapi_full_stack_launch-1.1.0.dist-info/entry_points.txt
fastapi_full_stack_launch-1.1.0.dist-info/top_level.txt
fastapi_full_stack_launch-1.1.0.dist-info/RECORD
