Metadata-Version: 2.4
Name: fastapi-full-stack-launch
Version: 1.1.0
Summary: A CLI tool to scaffold full-stack projects with FastAPI backend and React Vite frontend
Author: Krishi Devani
License-Expression: MIT
Project-URL: Homepage, https://pypi.org/project/fastapi-full-stack-launch/
Project-URL: Repository, https://github.com/krishi-devani/fastapi-full-stack-launch
Keywords: fullstack,fastapi,react,vite,cli,scaffold,project-generator,uv,typescript
Classifier: Development Status :: 4 - Beta
Classifier: Environment :: Console
Classifier: Intended Audience :: Developers
Classifier: Programming Language :: Python :: 3
Classifier: Programming Language :: Python :: 3.8
Classifier: Programming Language :: Python :: 3.9
Classifier: Programming Language :: Python :: 3.10
Classifier: Programming Language :: Python :: 3.11
Classifier: Programming Language :: Python :: 3.12
Classifier: Programming Language :: Python :: 3.13
Classifier: Operating System :: OS Independent
Classifier: Operating System :: POSIX :: Linux
Classifier: Operating System :: MacOS
Classifier: Operating System :: Microsoft :: Windows
Classifier: Topic :: Software Development :: Code Generators
Classifier: Topic :: Utilities
Requires-Python: >=3.8
